aceCommon/__init__.py
aceCommon/classCommon.py
aceCommon/fileCommon.py
aceCommon/listWorkCommon.py
aceCommon/mathCommon.py
aceCommon/osCommon.py
aceCommon/stringCommon.py
aceCommon/timeCommon.py
acecommon-0.1.1.dist-info/LICENSE
acecommon-0.1.1.dist-info/METADATA
acecommon-0.1.1.dist-info/WHEEL
acecommon-0.1.1.dist-info/top_level.txt
acecommon-0.1.1.dist-info/RECORD
