Metadata-Version: 2.1
Name: acecommon
Version: 0.1.1
Summary: A collection of common utility functions
Home-page: https://github.com/lukhed/aceCommon
Author: lukhed
Author-email: lukhed.mail@gmail.com
Classifier: Programming Language :: Python :: 3
Classifier: License :: OSI Approved :: MIT License
Classifier: Operating System :: OS Independent
Requires-Python: >=3.6
License-File: LICENSE
Requires-Dist: pytz>=2024.2
Requires-Dist: python-dateutil>=2.9.0
